discord_message_cleaner/__init__.py
discord_message_cleaner/providers/__init__.py
discord_message_cleaner/providers/version.py
discord_message_cleaner-0.1.1.dist-info/LICENSE
discord_message_cleaner-0.1.1.dist-info/LICENSE.md
discord_message_cleaner-0.1.1.dist-info/METADATA
discord_message_cleaner-0.1.1.dist-info/WHEEL
discord_message_cleaner-0.1.1.dist-info/entry_points.txt
discord_message_cleaner-0.1.1.dist-info/top_level.txt
discord_message_cleaner-0.1.1.dist-info/RECORD
