Metadata-Version: 2.1
Name: discord-message-cleaner
Version: 0.1.1
Summary: Cleans messages from a discord channel older than a set time in days
Home-page: https://github.com/rix1337/DiscordMessageCleaner
Author: rix1337
Author-email: 
Classifier: Programming Language :: Python :: 3
Classifier: License :: OSI Approved :: MIT License
Classifier: Operating System :: OS Independent
License-File: LICENSE
License-File: LICENSE.md
Requires-Dist: discord.py ==2.5.2
